httprunnerlt/__init__.py
httprunnerlt/__main__.py
httprunnerlt/cli.py
httprunnerlt/client.py
httprunnerlt/compat.py
httprunnerlt/exceptions.py
httprunnerlt/loader.py
httprunnerlt/make.py
httprunnerlt/models.py
httprunnerlt/parser.py
httprunnerlt/response.py
httprunnerlt/runner.py
httprunnerlt/scaffold.py
httprunnerlt/testcase.py
httprunnerlt/utils.py
httprunnerlt/app/__init__.py
httprunnerlt/app/main.py
httprunnerlt/app/routers/__init__.py
httprunnerlt/app/routers/debug.py
httprunnerlt/app/routers/debugtalk.py
httprunnerlt/app/routers/deps.py
httprunnerlt/builtin/__init__.py
httprunnerlt/builtin/comparators.py
httprunnerlt/builtin/functions.py
httprunnerlt/ext/__init__.py
httprunnerlt/ext/har2case/__init__.py
httprunnerlt/ext/har2case/core.py
httprunnerlt/ext/har2case/utils.py
httprunnerlt/ext/locust/__init__.py
httprunnerlt/ext/locust/locustfile.py
httprunnerlt/ext/uploader/__init__.py
httprunnerlt-0.0.5.dist-info/LICENSE
httprunnerlt-0.0.5.dist-info/METADATA
httprunnerlt-0.0.5.dist-info/WHEEL
httprunnerlt-0.0.5.dist-info/entry_points.txt
httprunnerlt-0.0.5.dist-info/top_level.txt
httprunnerlt-0.0.5.dist-info/RECORD
