Metadata-Version: 2.1
Name: httprunnerlt
Version: 0.0.5
Summary: this is fix assert
Home-page: http://www.example.com/~cschultz/bvote/
Author: liutao
Author-email: kongxuanr@163.com
License: MIT
Project-URL: Documentation, https://docs.locust.io/
Project-URL: Code, https://github.com/locustio/locust
Project-URL: Help/Questions, https://stackoverflow.com/questions/tagged/locust
Project-URL: Issue tracker, https://github.com/locustio/locust/issues
Project-URL: Home-page, http://www.baidu.com/
Platform: UNKNOWN
Classifier: Programming Language :: Python
Classifier: Programming Language :: Python :: 3.8
Requires-Python: >=3.6
Requires-Dist: loguru (==0.4.1)
Requires-Dist: urllib3 (==1.25.9)
Requires-Dist: filetype (==1.0.5)
Requires-Dist: pydantic (==1.8)
Requires-Dist: sentry-sdk (==0.14.4)
Requires-Dist: requests (==2.23.0)
Requires-Dist: pytest (==5.4.3)
Requires-Dist: jmespath (==0.9.5)
Requires-Dist: requests-toolbelt (==0.9.1)
Requires-Dist: Jinja2 (==2.10.3)
Requires-Dist: starlette (==0.13.6)
Requires-Dist: colorama (==0.4.4)
Requires-Dist: fastapi (==0.63.0)
Requires-Dist: PyYAML (==5.4.1)
